mrbios/__init__.py
mrbios/__main__.py
mrbios/cli.py
mrbios/core/__init__.py
mrbios/core/dir_obj.py
mrbios/core/env_build.py
mrbios/core/platform.py
mrbios/core/project.py
mrbios/core/runner.py
mrbios/templates/envs/py-env/build.yaml.temp
mrbios/templates/envs/r-env/build.yaml.temp
mrbios/templates/file_format/README.md
mrbios/templates/file_format/example_file.txt
mrbios/templates/file_type/README.md.temp
mrbios/templates/root/README.md
mrbios/templates/script/py-script/README.md.temp
mrbios/templates/script/py-script/interface.yaml
mrbios/templates/script/py-script/run.py
mrbios/templates/script/r-script/README.md.temp
mrbios/templates/script/r-script/interface.yaml
mrbios/templates/script/r-script/run.R
mrbios/templates/task/README.md.temp
mrbios/utils/__init__.py
mrbios/utils/log.py
mrbios/utils/misc.py
mrbios/utils/template.py
mrbios/utils/user_setting.py
mrbios-0.1.0.dist-info/LICENSE
mrbios-0.1.0.dist-info/METADATA
mrbios-0.1.0.dist-info/WHEEL
mrbios-0.1.0.dist-info/entry_points.txt
mrbios-0.1.0.dist-info/top_level.txt
mrbios-0.1.0.dist-info/RECORD
